pygitsync/VERSION
pygitsync/__init__.py
pygitsync/_configuration.py
pygitsync/_declarations.py
pygitsync/_default_values.py
pygitsync/_repo.py
pygitsync/_url.py
pygitsync/_utility.py
pygitsync/_version.py
pygitsync/entrypoint.py
pygitsync/exceptions.py
pygitsync/py.typed
pygitsync-0.2.0.post2.dist-info/entry_points.txt
pygitsync-0.2.0.post2.dist-info/LICENSE
pygitsync-0.2.0.post2.dist-info/WHEEL
pygitsync-0.2.0.post2.dist-info/METADATA
pygitsync-0.2.0.post2.dist-info/RECORD
