Metadata-Version: 2.1
Name: pygitsync
Version: 0.2.0.post2
Summary: Periodically sync files from a remote git repository.
Home-page: https://gitlab.com/ci-cd-devops/pygitsync
Author: Russell Smiley
Author-email: russell@blueskyjunkie.ca
Requires-Python: >=3.8
Classifier: Intended Audience :: Developers
Classifier: Intended Audience :: System Administrators
Classifier: License :: OSI Approved :: MIT License
Classifier: Programming Language :: Python :: 3 :: Only
Classifier: Topic :: System :: Software Distribution
Classifier: Typing :: Typed
Requires-Dist: aiofiles >=0.8.0, <1
Requires-Dist: click >=8.1.3, <9
Requires-Dist: click_logging_config >=0.1, <1
Requires-Dist: gitpython >=3.1.27, <4
Requires-Dist: parver >=0.3.1, <1
Requires-Dist: pydantic >=1.9.1, <2
Requires-Dist: python-daemon >=2.3.0, <3
Requires-Dist: ruamel.yaml >=0.17.21, <1
Requires-Dist: build_harness >=2, <3 ; extra == "dev"
Requires-Dist: pre_commit >=2.13.0, <3 ; extra == "dev"
Requires-Dist: types-aiofiles >=0.8.10, <1 ; extra == "dev"
Requires-Dist: sphinx >=4.0.2, <5 ; extra == "doc"
Requires-Dist: sphinx_rtd_theme >=1.0, <2 ; extra == "doc"
Requires-Dist: pytest >=7.1.1, <8 ; extra == "test"
Requires-Dist: pytest-asyncio >=0.18.3, <1 ; extra == "test"
Requires-Dist: pytest-cov >=3.0, <4 ; extra == "test"
Requires-Dist: pytest-mock >=3.6.1, <4 ; extra == "test"
Provides-Extra: dev
Provides-Extra: doc
Provides-Extra: test
